forager_task/__init__.py
forager_task/config.py
forager_task/main.py
forager_task/src/__init__.py
forager_task/src/command_abstract.py
forager_task/src/command_factory.py
forager_task/src/storage_service_abstract.py
forager_task/src/api_services/__init__.py
forager_task/src/api_services/hunter_api_service.py
forager_task/src/commands/__init__.py
forager_task/src/commands/delete_record_command.py
forager_task/src/commands/domain_search_command.py
forager_task/src/commands/email_verification_command.py
forager_task/src/commands/get_record_command.py
forager_task/src/services/__init__.py
forager_task/src/services/storage_service_json.py
forager_task/src/services/storage_service_sqlite.py
forager_task-1.0.3.dist-info/METADATA
forager_task-1.0.3.dist-info/WHEEL
forager_task-1.0.3.dist-info/top_level.txt
forager_task-1.0.3.dist-info/RECORD
